{
    "display": {
        "icon": {
            "item": "dust:spellpaper"
        },
        "title": {
            "translate": "advancements.dust.threedustspellscrolls.title"
        },
        "description": {
            "translate": "advancements.dust.threedustspellscrolls.description"
        }
    },
    "show_toast": true,
    "announce_to_chat": true,
    "hidden": true,
    "parent": "dust:dust/twodust",
    "criteria": {
        "spellscroll": {
            "trigger": "minecraft:inventory_changed",
            "conditions": {
                "items": [
                    {
                        "item": "dust:spellpaper"
                    }
                ]
            }
        }

    },
    "requirements": [
        ["spellscroll"]
    ]

}
