{
    "display": {
        "icon": {
            "item": "dust:red/saplingred"
        },
        "title": {
            "translate": "advancements.dust.twosapling.title"
        },
        "description": {
            "translate": "advancements.dust.twosapling.description"
        }
    },
    "show_toast": true,
    "announce_to_chat": true,
    "hidden": true,
    "parent": "dust:dust/root",
    "criteria": {
        "red": {
            "trigger": "minecraft:inventory_changed",
            "conditions": {
                "items": [
                    {
                        "item": "dust:red/saplingred"
                    }
                ]
            }
        },
        "blue": {
            "trigger": "minecraft:inventory_changed",
            "conditions": {
                "items": [
                    {
                        "item": "dust:blue/saplingblue"
                    }
                ]
            }
        },
        "yellow": {
            "trigger": "minecraft:inventory_changed",
            "conditions": {
                "items": [
                    {
                        "item": "dust:yellow/saplingyellow"
                    }
                ]
            }
        },
        "purple": {
            "trigger": "minecraft:inventory_changed",
            "conditions": {
                "items": [
                    {
                        "item": "dust:purple/saplingpurple"
                    }
                ]
            }
        },
        "green": {
            "trigger": "minecraft:inventory_changed",
            "conditions": {
                "items": [
                    {
                        "item": "dust:green/saplinggreen"
                    }
                ]
            }
        },
        "orange": {
            "trigger": "minecraft:inventory_changed",
            "conditions": {
                "items": [
                    {
                        "item": "dust:orange/saplingorange"
                    }
                ]
            }
        },
        "white": {
            "trigger": "minecraft:inventory_changed",
            "conditions": {
                "items": [
                    {
                        "item": "dust:white/saplingwhite"
                    }
                ]
            }
        },
        "black": {
            "trigger": "minecraft:inventory_changed",
            "conditions": {
                "items": [
                    {
                        "item": "dust:black/saplingblack"
                    }
                ]
            }
        }
    },
    "requirements": [
        ["red", "yellow", "blue", "purple", "green", "orange", "white", "black"]
    ]

}
